[{"id":"1","embassies":"Embassy of the Republic of Azerbaijan","tell":"021-22215191\/22212554","fax":"021-22217504","address":"Farmanieh-Andarzgoo Street- No.4 Shahid Vatanpour Road."},{"id":"2","embassies":"Embassy of the Republic of Argentina","tell":"021-22575555\/22577433\/22575932\/22575935","fax":"021-22577432","address":"Darrus- Yar Mohammadi Road- Ghoo Street #11"},{"id":"3","embassies":"Embassy of Germany","tell":"021-39991920\/39991140\/39990000","fax":"021-39991890","address":"Ferdowsi Ave- No.320-324"},{"id":"4","embassies":"Embassy of Austria","tell":"021-22750038\/22750040-42","fax":"021-22705262","address":"Niavaran- Ghodoosi Ave. #6 Mir Vali."},{"id":"5","embassies":"Embassy of Jordan","tell":"021-88088356\/88088351","fax":"021-88080496","address":"Ghods Town- Phase 4- North of Zarafshan- Street #2 No.7"},{"id":"6","embassies":"Embassy of the Republic of Armenia","tell":"021-66704833","fax":"021-66700657","address":"Jomhori Islami Ave. Shahriar Street. No.1"},{"id":"7","embassies":"Interests Section Office of the Unites States of America in the Swiss Embassy","tell":"021-22542178\/22565273","fax":"021-22580432","address":"Pasdaran- Shahid Moosavi St.(5th Golestan) No.39"},{"id":"8","embassies":"Embassy of the Eastern Republic of Uruguay","tell":"021-88679690-91","fax":"021-88782321","address":"Africa Hwy- Mina Blvd. No.5"},{"id":"9","embassies":"Embassy of the Republic of Uzbekistan","tell":"021-22832071\/22299780","fax":"021-22299158","address":"Aghdasieh-Bostan Ave. Nastaran Street. No.6"},{"id":"10","embassies":"Embassy of the Kingdom of Spain","tell":"021-22568681-4","fax":"021-22568017\/22568018","address":"Darrus-Shahrzad Blvd.Kamasayee Street.(first east st.) No.10"},{"id":"11","embassies":"Embassy of Australia","tell":"021-83863666","fax":"021-88720484\/88720490","address":"Khaled Islamboli St. Street 23. No.13"},{"id":"12","embassies":"Embassy of Slovak Republic","tell":"021-22424847\/22411164","fax":"021-22406496","address":"Vali Asr Street-Zaferanieh-Sar Lashkar FalahiAve.No. 34"},{"id":"13","embassies":"Embassy of the Republic of Slovenia","tell":"021-22836042","fax":"021-22290853","address":"Pasdaran-Farmanieh Square- 8th Naranjestan. No.28"},{"id":"14","embassies":"Embassy of the Republic of South Africa","tell":"021-22702866-9","fax":"021-22719558","address":"Tajrish-Vali Asr Ave.Fedows Garden-Yekta Street. No.5"},{"id":"15","embassies":"Embassy of the Islamic Republic of Afghanistan","tell":"021-88502666\/88735040\/88737531","fax":"021-88735600\/88733088","address":"Doctor Shahidi Ave- Pakistan Street. (beside the 4th St.)"},{"id":"16","embassies":"Embassy of the Republic of Ecuador","tell":"021-26203177\/26203178","fax":"021-26203179","address":"Vali Asr Ave-(front of Melat Park) Mandela Street. No.66"},{"id":"17","embassies":"People's Democratic Republic of Algeria","tell":"021-22420015-16","fax":"021-22420017","address":"Velenjak- 16th Street. No.6"},{"id":"18","embassies":"Embassy of The United Arabic Emirates","tell":"021-88781333-4\/88788515","fax":"021-88789084","address":"Vali Asr Ave-Vahid Dastgerdi Street. No.355"},{"id":"19","embassies":"Embassy of Indonesia","tell":"021-88716865","fax":"021-88718822","address":"Ghaem Magham Farahani Street. No.210"},{"id":"20","embassies":"Embassy of the United Kingdom of Great Britian","tell":"021-64052000\/64052219\/64052289\/64052405","fax":"021-64052289\/64052287","address":"Ferdowsi Ave-No.198"},{"id":"21","embassies":"Embassy of Ukraine","tell":"021-22417905\/22417901\/22404083\/22417920","fax":"021-22417921\/22404081","address":"Velenjak Street (between 18th and 20th Street) No.44"},{"id":"22","embassies":"Embassy of the Republic of Uganda","tell":"021-22633198\/22600465","fax":"021-22009764","address":"Dastgerdi Ave. Deliri Blvd. Nonahalan Street (Naz St) No.19"},{"id":"23","embassies":"Ebmassy of the Republic of Italy","tell":"021-66726955-7","fax":"021-22297618\/22286933","address":"Hafez Street-Nofel Lochatoo-No.81"},{"id":"24","embassies":"Embassy of Ireland","tell":"021-22803835","fax":"021-22297618\/22286933","address":"Shahid Lavasani Ave-Bazdar St. No.5"},{"id":"25","embassies":"Embassy of the Kingdom of Bahrain","tell":"021-88773383\/88775365\/88772079","fax":"021-88779112\/88880276","address":"Africa Ave-(before Jahan-Kodak) Corner of Zobian St. No.248"},{"id":"26","embassies":"Embassy of the Federative Republic of Brazil","tell":"021-22753108-10","fax":"021-22752009","address":"Zaferanieh-Vali Asr Street. Shahid Falahi St. No.26"},{"id":"27","embassies":"Embassy of the Republic of Belarus","tell":"021-22752229","fax":"021-22751382","address":"Shahid Falahi Street.(Zaferanieh)Shahid Taheri St.Azar Alley No1"},{"id":"28","embassies":"Embassy of Belgium","tell":"021-22041617\/22049247\/22040073","fax":"021-22044608","address":"Elahie-Shahid Fayazi (fereshte)- No.155-157"},{"id":"29","embassies":"Embassy of the Republic of Bulgaria","tell":"021-88775662\/88775037","fax":"021-88779680","address":"Vali Asr- Shahid Dr Abbaspour-Nezami Ganjoye-No.16\/18"},{"id":"30","embassies":"Embassy of the People's Republic of Bangladesh","tell":"021-88063073-6","fax":"021-88039965","address":"Vanak Square-Vanak Street-Next to Maryam Alley-No.58"},{"id":"31","embassies":"Embassy of the Republic of Bosnia and Herzegovina","tell":"021-88092728\/88086929-30","fax":"021-88092120","address":"Shahrake Gharb-Iran Zamin- 4th Street- Aban Alley- No.485"},{"id":"32","embassies":"Embassy of the Republic of Bolivia","tell":"021-88685070","fax":"021-88685073","address":"Saad Abad-Kosar Square-Ghore Tape Alley- No.79 (Second Floor)"},{"id":"33","embassies":"Embassy of the Islamic Republic of Pakistan","tell":"021-66941388-91\/66944888","fax":"021-66944898\/66944889","address":"North Amir Abad-Dr Hossein Fatemi Street-Etemadzade Alley.No1"},{"id":"34","embassies":"Embassy of Portugal","tell":"021-22764060\/22582760","fax":"021-2252668","address":"Darrus-Hedayat Street. Rozbeh Alley- No.16"},{"id":"35","embassies":"Embassy of the Republic of Tajikistan","tell":"021-22299584\/2283465","fax":"021-22809299\/22809249","address":"Niavaran-Shahid Zeinali Street- 3rd Alley- No.10"},{"id":"36","embassies":"Embassy of the Kingdom of Thailand","tell":"021-77643297-9\/77531433","fax":"021-77532022","address":"Baherestan-Esteghlal Alley- No.4"},{"id":"37","embassies":"Embassy of Turkmenistan","tell":"021-22206731\/22206306","fax":"021-22206732","address":"Farmanieh-Dr Lavasani Street- Vatanpoor St.No.5"},{"id":"38","embassies":"Embassy of the Republic of Turkey","tell":"021-35951100\/33111202\/33115351","fax":"021-33117928\/35951136","address":"Ferdowsi Street. No.337"},{"id":"39","embassies":"Embassy of the Republic of Tunisia","tell":"021-22009203\/22632384","fax":"021-22631994","address":"Elahieh-Shahid Fayazi. No.43"},{"id":"40","embassies":"Embassy of the Czech Republic","tell":"021-22288149\/22288153","fax":"021-22802079","address":"Farmanieh-Dr Lavasani Street- (corner of yas) No.199"},{"id":"41","embassies":"Embassy of the People's Republic of China","tell":"021-22291240\/22291241\/22292566","fax":"021-22290690","address":"Pasdaran-7th st. of Narenjestan .No.13"},{"id":"42","embassies":"Embassy of the Kingdom of Denmark","tell":"021-22601363\/22607020","fax":"021-22640007","address":"Elahieh-Dr Shariati Street- Dashti St. No.28"},{"id":"43","embassies":"Embassy of Russia","tell":"021-66701161\/66701163","fax":"021-66701652","address":"Nofel Loshaato Street. No.39"},{"id":"44","embassies":"Embassy of Romania","tell":"021-77647570\/77534658","fax":"021-77535291","address":"Baherestan Street. Fakhr Abad St. No.22"},{"id":"45","embassies":"Embassy of New Zealand","tell":"021-26122175-7","fax":"021-26121973","address":"Niavaran-Aghdasieh-North Golestan Complex-(corner of susan st.)No.34"},{"id":"46","embassies":"Embassy of the Republic of Zimbabwe","tell":"021-22027553-7","fax":"021-22049084","address":"Shahrake Gharb-Phase 4-Zarafshan St. No.1610"},{"id":"47","embassies":"Embassy of Japan","tell":"021-88717922\/88717923\/88713396","fax":"021-88713515","address":"Bokharest Street. Corner of 5th St. No.12"},{"id":"48","embassies":"Embassy of the Republic of Ivory Coast","tell":"021-22404150\/22428794","fax":"021-22400938","address":"Velenjak-18th Street- No.4"},{"id":"49","embassies":"Democratic Socialist Republic of Sri Lanka","tell":"021-22569179\/22768630\/22768631","fax":"021-22540924","address":"Gheitarieh-Jahantaab St- No.25"},{"id":"50","embassies":"Embassy of Sweden","tell":"021-22296802\/23712200","fax":"021-22286021","address":"North Farmanieh-Pasdaran St-Bostan St,(corner of nastaran)No.27"},{"id":"51","embassies":"Embassy of Switzerland","tell":"021-22008333\/22008454","fax":"021-22006002","address":"Elahie-Bostan St.Sharifi Manesh St-Yasaman Alley. No.13"},{"id":"52","embassies":"Embassy of Sudan","tell":"021-88781183-4","fax":"021-88792331","address":"Africa Street-(front of gas station)Babak Bahrami Alley- No.39"},{"id":"53","embassies":"Embassy of the Syrian Arabic Republic","tell":"021-22059031-2\/22055332","fax":"021-22059409","address":"Africa Street-Iraj St- No19"},{"id":"54","embassies":"Embassy of Somalia","tell":"021-22673837","fax":"021-22245146","address":"Shariati Street-Mirzapour St-(beginning of hadadian) No.1"},{"id":"55","embassies":"Embassy of the Republic of Sierra Leone","tell":"021-22291619","fax":"021-22282977","address":"Aghdasieh Street. Firoozbakhsh St.Kamran St- No.1"},{"id":"56","embassies":"Embassy of Serbia","tell":"021-22412569-71","fax":"021-22402869","address":"Velenjak-9th Street. No.12"},{"id":"57","embassies":"Embassy of the Republic of Iraq","tell":"021-88938865-6","fax":"021-88938877","address":"Vali Asr Street, Dameshgh St"},{"id":"58","embassies":"Embassy of the Kingdom of Saudi Arabia","tell":"021-22288543\/22299979","fax":"021-22294691","address":"Pasdaran (after farmanieh)- Bostan St. Nilofar St. No.24"},{"id":"59","embassies":"Embassy of the Sultanate of Oman","tell":"021-22056831-2\/22057641-2\/22056823","fax":"021-22044672","address":"Africa Blvd. Tandis Alley. No.12"},{"id":"60","embassies":"Embassy of the Republic of Ghana","tell":"021-22421447\/22175363","fax":"021-22421448\/26218378","address":"Zaferanieh-Amiri sori Street. No.5"},{"id":"61","embassies":"Embassy of the French Republic","tell":"021-64094000","fax":"021-64094092\/64094093","address":"Hafez Street. Nofel Loshato St. No.85"},{"id":"62","embassies":"Embassy of Palestine","tell":"021-66464501\/66402513","fax":"021-66465736","address":"Felestine Street. No.145"},{"id":"63","embassies":"Embassy of Finland","tell":"021-23512000","fax":"021-22236230","address":"Shariati Street. Mirzapour St.Hadadian Street. No.2"},{"id":"64","embassies":"Embassy of the Republic of the Philippines","tell":"021-22668774-6","fax":"021-22668990","address":"Vali Asr Street.Khayyam Street. No.9"},{"id":"65","embassies":"Embassy of the Republic of Cyprus","tell":"021-22219842\/22201240","fax":"021-22219843","address":"Tajrish-Dezashib- Shahid Karimi. No.194"},{"id":"66","embassies":"Embassy of Kyrgyz Republic","tell":"021-22830354","fax":"021-22281720","address":"Pasdaran-5th Naranjestan- No.12"},{"id":"67","embassies":"Embassy of the Republic of Kazakhstan","tell":"021-22565933-4","fax":"021-22546400","address":"Darrus-Hedayat Street(corner of the mosque) No.4"},{"id":"68","embassies":"Government of Qatar","tell":"021-22051255-6\/22029336-7","fax":"021-22058478","address":"Africa Hwy- Gol Azin Street- No.4"},{"id":"69","embassies":"Embassy of the Republic of Croatia","tell":"021-22589923\/22587039","fax":"021-22549199","address":"Pasdaran-1st Bahestan, No.19"},{"id":"70","embassies":"Embassy of the Republic of South Korea","tell":"021-88054900","fax":"021-88054899","address":"Vanak-Molasadra-Sheikh Bahaei St.North,West of Daneshvar.No.2"},{"id":"71","embassies":"Democratic People's Republic of North Korea","tell":"021-22232120\/22234260","fax":"021-22234261\/22230687","address":"Ghetarieh Blvd. Tavazoee St. First end.No.3"},{"id":"72","embassies":"Embassy of Kenya","tell":"021-22049967-8","fax":"021-22047951","address":"Africa Street. Mahyar St. No.13"},{"id":"73","embassies":"Embassy of the Republic of Cuba","tell":"021-22282749","fax":"021-22282749","address":"Niavaran Square- Khodavardi Street. West of 17th St.No.54"},{"id":"74","embassies":"Union of the Comoros","tell":"021-77624400","fax":"021-77624411","address":"Dr Shariati Street. Melk St. No.10"},{"id":"75","embassies":"Embassy of Kuwait","tell":"021-88785997-9","fax":"021-88779167\/88782252","address":"Africa-Vahid Dastjerdi- No.323"},{"id":"76","embassies":"Embassy of Georgia","tell":"021-22764129","fax":"021-22542692","address":"Pasdaran-Golestan 2- No.92"},{"id":"77","embassies":"Embassy of the Republic of Guinea","tell":"021-77535744","fax":"021-77535743","address":"Shariati Street. Melk St. No10"},{"id":"78","embassies":"Embassy of the Republic of Lebanon","tell":"021-88908451\/88805902\/88906051","fax":"021-88907345","address":"Sepahbod Gharni St. Shahid Kalantari St. No.31"},{"id":"79","embassies":"Embassy of the Republic of Poland","tell":"021-88787262-4","fax":"021-88788774","address":"Africa Blvd.Piruz St. No.1\/3"},{"id":"80","embassies":"Embassy of the Libyan Arabic Republic","tell":"021-22201677\/22235505\/22235812","fax":"021-22236649","address":"South Kamranieh- (end of Maryam St)- No.2"},{"id":"81","embassies":"Embassy of Malaysia","tell":"021-22046873","fax":"021-22046972","address":"Moghadas Ardebili St.Changizi Alley- No.6"},{"id":"82","embassies":"Embassy of Mali Republic","tell":"021-22207278\/22236591","fax":"021-22234631","address":"Dr.Ali Shariatii St.Romi Bridge- Istanbul St.Aroos Alley. No.16"},{"id":"83","embassies":"Embassy of the Republic of Hungary","tell":"021-22550452\/22550460","fax":"021-22550503","address":"Darrus-Hedayat Blvd. Shadloo St. No.10"},{"id":"84","embassies":"Diplomatic office Arabic Republic of Egypt","tell":"021-22242268\/22205202\/22214883","fax":"021-22211698","address":"Shariati St.(after romi bridge) Rezaei Alley-No.6\/8"},{"id":"85","embassies":"Embassy of the United States of Mexico","tell":"021-22057586-8\/22057590\/22012921","fax":"021-22057589","address":"Africa Hwy- Golfam Street. No.12"},{"id":"86","embassies":"Embassy of the Islamic Republic of Mauritania","tell":"021-77500074","fax":"021-77529515","address":"Shariati Street. Melk St. No.8 First Floor"},{"id":"87","embassies":"Embassy of the Kingdom of Norway","tell":"021-22291333\/22802143\/22806529","fax":"021-22292776","address":"Dr.Lavasan St. (Farmanieh)- Corner of Sonbol St. No.201"},{"id":"88","embassies":"The Federal Republic of Nigeria","tell":"021-88889621\/88206810","fax":"021-88799783\/88782254","address":"Africa Street. West of Zafar St. No.323"},{"id":"89","embassies":"Embassy of Nicaragua","tell":"021-88685070","fax":"021-88685073","address":"Saad Abad St. Ghare tapei St. No.79 4th Floor"},{"id":"90","embassies":"Embassy of Vatican","tell":"021-66403574","fax":"021-66419442","address":"Intersection of Nofel Loshato- Razi St. No.84"},{"id":"91","embassies":"Bolivarian Republic of Venezuela","tell":"021-26124599","fax":"021-26124886","address":"North of Kamranieh- Bazdar St- Tajiki St- No.17"},{"id":"92","embassies":"Socialist Republic of Vietnam","tell":"021-22411670","fax":"021-22416045","address":"Vali Asr- Moghadas Ardebili- Pasian St- Eastern Ordibehesht. No.6"},{"id":"93","embassies":"Embassy of the Kingdom of the Netherlands","tell":"021-23660000","fax":"021-23660190\/23660390","address":"Farmanieh- South Dibaji- Sonbol St. No.7"},{"id":"94","embassies":"Embassy of India","tell":"021-88755103-5","fax":"021-88755973\/88745557","address":"Dr Beheshti St. Mir Emad St (corner of the 9th st) No.22"},{"id":"95","embassies":"Embassy of the Republic of Yemen","tell":"021-22414446\/22416682\/22419910","fax":"021-22419934","address":"Zaferanieh-Shahid Falahi St. Shahid ejazi. No.87"},{"id":"96","embassies":"Embassy of Greece","tell":"021-22053784\/22050533","fax":"021-22057431\/22403665","address":"Africa St. Esfandiar Blvd. No.43"}]